leginorma/__init__.py
leginorma/api.py
leginorma/models.py
leginorma-0.0.4.dist-info/LICENSE
leginorma-0.0.4.dist-info/METADATA
leginorma-0.0.4.dist-info/WHEEL
leginorma-0.0.4.dist-info/top_level.txt
leginorma-0.0.4.dist-info/RECORD
